jomiel_kore/__init__.py
jomiel_kore/app.py
jomiel_kore/file.py
jomiel_kore/formatter.py
jomiel_kore/input.py
jomiel_kore/log.py
jomiel_kore/opts.py
jomiel_kore/sig.py
jomiel_kore/version.py
jomiel_kore-0.2.2.dist-info/LICENSE
jomiel_kore-0.2.2.dist-info/METADATA
jomiel_kore-0.2.2.dist-info/NOTICE
jomiel_kore-0.2.2.dist-info/WHEEL
jomiel_kore-0.2.2.dist-info/top_level.txt
jomiel_kore-0.2.2.dist-info/zip-safe
jomiel_kore-0.2.2.dist-info/RECORD
