Metadata-Version: 2.1
Name: jomiel-kore
Version: 0.2.2
Summary: Minimalistic foundation for creating new Python applications
Home-page: https://github.com/guendto/jomiel-kore
Author: Toni Gündoğdu
Author-email: 47444442+guendto@users.noreply.github.com
License: Apache2.0
Platform: any
Classifier: Development Status :: 4 - Beta
Classifier: License :: OSI Approved :: Apache Software License
Classifier: Programming Language :: Python :: 3.6
Classifier: Programming Language :: Python :: 3.7
Classifier: Programming Language :: Python :: 3.8
Classifier: Programming Language :: Python :: 3.9
Requires-Python: >=3.6
License-File: LICENSE
License-File: NOTICE
Requires-Dist: configargparse
Requires-Dist: deprecated
Requires-Dist: pyzmq
Requires-Dist: ruamel.yaml
Requires-Dist: ujson
Requires-Dist: validators
Requires-Dist: importlib-resources ; python_version < "3.7"
Requires-Dist: importlib-metadata ; python_version < "3.8"
